<?xml version="1.0" ?>
<manifest identifier="ID-F521FFA6-E31E-42E3-A79A-940A816AA999" version="1"
       xmlns="http://www.imsproject.org/xsd/imscp_rootv1p1p2"
       xmlns:adlcp="http://www.adlnet.org/xsd/adlcp_rootv1p2"
       xmlns:xsi="http://www.w3.org/2001/XMLSchema-instance"
       xsi:schemaLocation="http://www.imsproject.org/xsd/imscp_rootv1p1p2 imscp_rootv1p1p2.xsd
                           http://www.imsglobal.org/xsd/imsmd_rootv1p2p1 imsmd_rootv1p2p1.xsd
                           http://www.adlnet.org/xsd/adlcp_rootv1p2 adlcp_rootv1p2.xsd">
	<metadata>
		<schema>ADL SCORM</schema>
		<schemaversion>1.2</schemaversion>
        <lom xmlns="http://www.imsglobal.org/xsd/imsmd_rootv1p2p1"
                 xmlns:xsi="http://www.w3.org/2001/XMLSchema-instance"
                 xsi:schemaLocation="http://www.imsglobal.org/xsd/imsmd_rootv1p2p1 imsmd_rootv1p2p1.xsd">
            <general>
                <title>
                    <langstring xml:lang="en"></langstring>
                </title>
                <description>
                    <langstring xml:lang="en"></langstring>
                </description>
            </general>
        </lom>
	</metadata>
	<organizations default="B0">
		<organization identifier="B0">
			<title></title> 
			<item identifier="I_SCO0" identifierref="SCO0" isvisible="true">
            <title>(null)</title>
            <adlcp:masteryscore>80</adlcp:masteryscore>
        </item>

		</organization>
	</organizations>
	<resources>
	    <resource identifier="SCO0" type="webcontent" adlcp:scormtype="sco" href="scormVid.html">
            <file href="scormVid.html"/>
            <dependency identifierref="ALLRESOURCES" />
         </resource>

		<resource identifier="ALLRESOURCES" type="webcontent" adlcp:scormtype="asset">
            <file href="scormVid.html" />
<file href="scripts/techsmith-smart-player.min.js" />
<file href="scripts/embedded-smart-player.min.js" />
<file href="skins/techsmith-smart-player.min.css" />
<file href="scormVid_embed.css" />
<file href="scormVid_Player.html" />
<file href="media/scormVid.mp4" />
<file href="scormVid_config.xml" />
<file href="media/FirstFrame.png" />

         </resource>
	</resources>
</manifest>

